pyfrogsay/__init__.py
pyfrogsay/__main__.py
pyfrogsay/main.py
pyfrogsay-1.0.1.dist-info/METADATA
pyfrogsay-1.0.1.dist-info/WHEEL
pyfrogsay-1.0.1.dist-info/entry_points.txt
pyfrogsay-1.0.1.dist-info/top_level.txt
pyfrogsay-1.0.1.dist-info/RECORD
