Metadata-Version: 2.4
Name: pyfrogsay
Version: 1.0.1
Summary: A talking frog in python inspired by pycowsay
Requires-Python: >=3.0
